message.py
telegrambotalarm.py
telegram_coffee_break-0.2.1.dist-info/LICENSE
telegram_coffee_break-0.2.1.dist-info/METADATA
telegram_coffee_break-0.2.1.dist-info/WHEEL
telegram_coffee_break-0.2.1.dist-info/top_level.txt
telegram_coffee_break-0.2.1.dist-info/RECORD
