Metadata-Version: 2.1
Name: telegram-coffee-break
Version: 0.2.1
Summary: send telegram notification using a bot
Home-page: https://github.com/RomainGratier/telegram-coffee-break
Author: Romain Gratier
Author-email: romain.gratier@gmail.com
License: MIT
Keywords: python telegram
Platform: UNKNOWN
Classifier: Programming Language :: Python :: 3.7
Classifier: Operating System :: OS Independent
Classifier: License :: OSI Approved :: MIT License
